[{"@odata.etag":"","ItemInternalId":"ac6de808-a916-45a9-b475-e3679b9e6309","Order_nr":"3963886","Item_nr":"300456","Order_name":"Rødløk ternet 10x10 mm 10 kg","Status":"ReportedFinished","Prod_group":"Industri","Prod_pool":"SF-po-Ind2","Site":"BI-Tranby","Date_delivery":"2026-07-24T12:00:00Z","QTY_scheduled":"550","QTY_good":"550","QTY_remaining":"0","PCT_done":"100"},{"@odata.etag":"","ItemInternalId":"8618a7f6-dd95-412b-b2bb-481f8d9740c9","Order_nr":"3963895","Item_nr":"300385","Order_name":"Babyleaf Mix 250 g","Status":"StartedUp","Prod_group":"Storkjøkken","Prod_pool":"SF-pm10","Site":"BI-Tranby","Date_delivery":"2026-07-24T12:00:00Z","QTY_scheduled":"40","QTY_good":"0","QTY_remaining":"40","PCT_done":"0"},{"@odata.etag":"","ItemInternalId":"d2134e10-f151-4128-bc59-b83d6ad3edb3","Order_nr":"3963901","Item_nr":"HF200123","Order_name":"HF Råkost med rødkål og purre","Status":"StartedUp","Prod_group":"HF Trim","Prod_pool":"SF-T2","Site":"BI-Tranby","Date_delivery":"2026-07-24T12:00:00Z","QTY_scheduled":"82.47","QTY_good":"84","QTY_remaining":"0","PCT_done":"102"},{"@odata.etag":"","ItemInternalId":"b03a2904-8ddd-48a5-b706-6c6b01975c61","Order_nr":"3963903","Item_nr":"HF200002","Order_name":"HF Babyleaf mix","Status":"ReportedFinished","Prod_group":"HF Trim","Prod_pool":"SF-T6","Site":"BI-Tranby","Date_delivery":"2026-07-24T12:00:00Z","QTY_scheduled":"10.31","QTY_good":"12.4","QTY_remaining":"0","PCT_done":"120"},{"@odata.etag":"","ItemInternalId":"c74fb05e-f4ea-48e0-9fa8-b0ffc264ecb3","Order_nr":"3963907","Item_nr":"HF200050","Order_name":"HF Gulrot julienne","Status":"ReportedFinished","Prod_group":"HF Kuttetorg","Prod_pool":"SF-K2","Site":"BI-Tranby","Date_delivery":"2026-07-24T12:00:00Z","QTY_scheduled":"29.76","QTY_good":"31.6","QTY_remaining":"0","PCT_done":"106"},{"@odata.etag":"","ItemInternalId":"5f46561a-6e5b-45f3-94e5-2af4c2b02d07","Order_nr":"3962491","Item_nr":"300463","Order_name":"Hodekål ternet vasket 10 kg","Status":"ReportedFinished","Prod_group":"Industri","Prod_pool":"SF-po-Ind1","Site":"BI-Tranby","Date_delivery":"2026-07-24T12:00:00Z","QTY_scheduled":"60","QTY_good":"60","QTY_remaining":"0","PCT_done":"100"},{"@odata.etag":"","ItemInternalId":"c2ec4a92-4a0e-4994-9085-8693e06fe415","Order_nr":"3962527","Item_nr":"303010","Order_name":"Paprika grønn 10x10mm 5 kg","Status":"ReportedFinished","Prod_group":"Industri","Prod_pool":"SF-po-Ind1","Site":"BI-Tranby","Date_delivery":"2026-07-24T12:00:00Z","QTY_scheduled":"40","QTY_good":"40","QTY_remaining":"0","PCT_done":"100"},{"@odata.etag":"","ItemInternalId":"6a52d922-961c-41f7-bbae-51923e05894e","Order_nr":"3962529","Item_nr":"303100","Order_name":"Agurk strimlet 600g 1/6 GN SB","Status":"ReportedFinished","Prod_group":"Beger","Prod_pool":"SF-be-Gast","Site":"BI-Tranby","Date_delivery":"2026-07-24T12:00:00Z","QTY_scheduled":"80","QTY_good":"84","QTY_remaining":"0","PCT_done":"105"},{"@odata.etag":"","ItemInternalId":"700d2601-6469-4831-90e0-223bba882591","Order_nr":"3962549","Item_nr":"300224","Order_name":"Råkost Mix 250g NG","Status":"ReportedFinished","Prod_group":"Dagligvare","Prod_pool":"SF-p-Me-WA","Site":"BI-Tranby","Date_delivery":"2026-07-24T12:00:00Z","QTY_scheduled":"1700","QTY_good":"1776","QTY_remaining":"0","PCT_done":"104"},{"@odata.etag":"","ItemInternalId":"12a02b71-2734-494b-b7f7-16b924bcff81","Order_nr":"3962559","Item_nr":"300112","Order_name":"Romano Mix 175g NG","Status":"ReportedFinished","Prod_group":"Dagligvare","Prod_pool":"SF-p-Va-WA","Site":"BI-Tranby","Date_delivery":"2026-07-24T12:00:00Z","QTY_scheduled":"3100","QTY_good":"2982","QTY_remaining":"118","PCT_done":"96"},{"@odata.etag":"","ItemInternalId":"496d9299-7fc7-4fb2-adb1-c178b8386429","Order_nr":"3962587","Item_nr":"300302","Order_name":"Grønnkål Mix 300 g NG","Status":"StartedUp","Prod_group":"Dagligvare","Prod_pool":"SF-p-Va-WA","Site":"BI-Tranby","Date_delivery":"2026-07-24T12:00:00Z","QTY_scheduled":"800","QTY_good":"0","QTY_remaining":"800","PCT_done":"0"},{"@odata.etag":"","ItemInternalId":"4626ad8a-93dc-434e-9964-716c46a605db","Order_nr":"3962615","Item_nr":"300543","Order_name":"Råkostblanding m/rødkål og purre 1 kg","Status":"ReportedFinished","Prod_group":"Storkjøkken","Prod_pool":"SF-p-Gr-SK","Site":"BI-Tranby","Date_delivery":"2026-07-24T12:00:00Z","QTY_scheduled":"120","QTY_good":"205","QTY_remaining":"0","PCT_done":"171"},{"@odata.etag":"","ItemInternalId":"da3c3687-b62c-4cbf-b5d3-c8510022c7d8","Order_nr":"3962671","Item_nr":"BI620120","Order_name":"Babyspinat 125 g SB","Status":"StartedUp","Prod_group":"Storkjøkken","Prod_pool":"SF-p-Gr-SK","Site":"BI-Tranby","Date_delivery":"2026-07-24T12:00:00Z","QTY_scheduled":"110","QTY_good":"0","QTY_remaining":"110","PCT_done":"0"},{"@odata.etag":"","ItemInternalId":"588a5c77-dfe3-473d-bb53-98e8691aa1d7","Order_nr":"3962673","Item_nr":"303578","Order_name":"Paprika grønn skivet 500 g","Status":"ReportedFinished","Prod_group":"Storkjøkken","Prod_pool":"SF-p-Gr-SK","Site":"BI-Tranby","Date_delivery":"2026-07-24T12:00:00Z","QTY_scheduled":"80","QTY_good":"80","QTY_remaining":"0","PCT_done":"100"},{"@odata.etag":"","ItemInternalId":"e00c36ee-38d4-4a4e-84c7-f7146d107865","Order_nr":"3962699","Item_nr":"300249","Order_name":"Kyllingsalat 225g  NG","Status":"StartedUp","Prod_group":"Beger","Prod_pool":"SF-be-3KB","Site":"BI-Tranby","Date_delivery":"2026-07-24T12:00:00Z","QTY_scheduled":"300","QTY_good":"304","QTY_remaining":"0","PCT_done":"101"},{"@odata.etag":"","ItemInternalId":"c7ee75df-3fec-4c25-a3a6-b0a6846304f9","Order_nr":"3962701","Item_nr":"300315","Order_name":"Grønnkål 150 g 6 po/ks NG","Status":"StartedUp","Prod_group":"Dagligvare","Prod_pool":"SF-p-Va-WA","Site":"BI-Tranby","Date_delivery":"2026-07-24T12:00:00Z","QTY_scheduled":"1000","QTY_good":"0","QTY_remaining":"1000","PCT_done":"0"},{"@odata.etag":"","ItemInternalId":"967bfe4a-b7ec-40fc-8615-f31d93bc41d5","Order_nr":"3962707","Item_nr":"300499","Order_name":"Gul løk ternet 5x5 mm 10 kg","Status":"ReportedFinished","Prod_group":"Annet","Prod_pool":"SF-po-Ind3","Site":"BI-Tranby","Date_delivery":"2026-07-24T12:00:00Z","QTY_scheduled":"10","QTY_good":"10","QTY_remaining":"0","PCT_done":"100"},{"@odata.etag":"","ItemInternalId":"643eff2b-110e-4427-a812-2ced5911f7dc","Order_nr":"3962745","Item_nr":"301144","Order_name":"Purre ternet 10 kg","Status":"ReportedFinished","Prod_group":"Annet","Prod_pool":"SF-po-Ind3","Site":"BI-Tranby","Date_delivery":"2026-07-24T12:00:00Z","QTY_scheduled":"10","QTY_good":"10","QTY_remaining":"0","PCT_done":"100"},{"@odata.etag":"","ItemInternalId":"dd9b7366-4ffe-4838-952d-a1f254b5fd05","Order_nr":"3962841","Item_nr":"300409","Order_name":"Wok Mix 1 kg","Status":"ReportedFinished","Prod_group":"Storkjøkken","Prod_pool":"SF-p-Gr-SK","Site":"BI-Tranby","Date_delivery":"2026-07-24T12:00:00Z","QTY_scheduled":"20","QTY_good":"30","QTY_remaining":"0","PCT_done":"150"},{"@odata.etag":"","ItemInternalId":"daea1367-508f-48e0-af83-1d9486898bf2","Order_nr":"3962863","Item_nr":"300518","Order_name":"Paprika gul 15x20 mm 5 kg","Status":"StartedUp","Prod_group":"Annet","Prod_pool":"SF-po-Ind3","Site":"BI-Tranby","Date_delivery":"2026-07-24T12:00:00Z","QTY_scheduled":"10","QTY_good":"10","QTY_remaining":"0","PCT_done":"100"},{"@odata.etag":"","ItemInternalId":"7e3b7088-450a-4a48-a78d-9101c0dfeaed","Order_nr":"3962865","Item_nr":"300126","Order_name":"Salatbar Basis 500 g SB","Status":"StartedUp","Prod_group":"Storkjøkken","Prod_pool":"SF-pm10","Site":"BI-Tranby","Date_delivery":"2026-07-24T12:00:00Z","QTY_scheduled":"110","QTY_good":"136","QTY_remaining":"0","PCT_done":"124"},{"@odata.etag":"","ItemInternalId":"82c86144-22fc-4ccd-a1e8-6a9ce6adc297","Order_nr":"3962867","Item_nr":"300444","Order_name":"Hodekål finstrimlet 1 kg","Status":"ReportedFinished","Prod_group":"Storkjøkken","Prod_pool":"SF-p-Gr-SK","Site":"BI-Tranby","Date_delivery":"2026-07-24T12:00:00Z","QTY_scheduled":"160","QTY_good":"170","QTY_remaining":"0","PCT_done":"106"},{"@odata.etag":"","ItemInternalId":"42d6bd9c-84cd-47a5-ac69-3c07f519d367","Order_nr":"3962869","Item_nr":"300301","Order_name":"Isberg Mix 250 g 6 po/ks NG","Status":"ReportedFinished","Prod_group":"Dagligvare","Prod_pool":"SF-p-Va-WA","Site":"BI-Tranby","Date_delivery":"2026-07-24T12:00:00Z","QTY_scheduled":"3300","QTY_good":"3306","QTY_remaining":"0","PCT_done":"100"},{"@odata.etag":"","ItemInternalId":"de0e470d-f1d3-440e-b725-c8785144bfde","Order_nr":"3962917","Item_nr":"301910","Order_name":"Crispi Mix 175 g NG","Status":"StartedUp","Prod_group":"Dagligvare","Prod_pool":"SF-p-Va-WA","Site":"BI-Tranby","Date_delivery":"2026-07-24T12:00:00Z","QTY_scheduled":"1700","QTY_good":"1776","QTY_remaining":"0","PCT_done":"104"},{"@odata.etag":"","ItemInternalId":"d1f9e3a8-5fa2-42f8-9073-fc0cf1b95a8d","Order_nr":"3962919","Item_nr":"300250","Order_name":"Brokkolisalat 260 g NG","Status":"StartedUp","Prod_group":"Beger","Prod_pool":"SF-be-180x","Site":"BI-Tranby","Date_delivery":"2026-07-24T12:00:00Z","QTY_scheduled":"600","QTY_good":"588","QTY_remaining":"12","PCT_done":"98"},{"@odata.etag":"","ItemInternalId":"c50de510-d1f0-4367-b393-17261ef8f57e","Order_nr":"3962921","Item_nr":"300211","Order_name":"Wok Mix 300g NG","Status":"StartedUp","Prod_group":"Dagligvare","Prod_pool":"SF-p-Me-WA","Site":"BI-Tranby","Date_delivery":"2026-07-24T12:00:00Z","QTY_scheduled":"1100","QTY_good":"1080","QTY_remaining":"20","PCT_done":"98"},{"@odata.etag":"","ItemInternalId":"d413f882-ebc4-4b3a-9dd1-0ed239b4c1e8","Order_nr":"3962937","Item_nr":"300203","Order_name":"Meksikansk Mix 270 g NG","Status":"ReportedFinished","Prod_group":"Dagligvare","Prod_pool":"SF-p-MP-WA","Site":"BI-Tranby","Date_delivery":"2026-07-24T12:00:00Z","QTY_scheduled":"1700","QTY_good":"1740","QTY_remaining":"0","PCT_done":"102"},{"@odata.etag":"","ItemInternalId":"0984105a-87a6-437a-8a50-4b1e64633790","Order_nr":"3962943","Item_nr":"300520","Order_name":"Kålrot ternet rå 5 kg","Status":"ReportedFinished","Prod_group":"Vakuum","Prod_pool":"SF-po-Vaku","Site":"BI-Tranby","Date_delivery":"2026-07-24T12:00:00Z","QTY_scheduled":"2","QTY_good":"2","QTY_remaining":"0","PCT_done":"100"},{"@odata.etag":"","ItemInternalId":"03ed875f-60b2-4f61-be68-2f0bb75fc361","Order_nr":"3962969","Item_nr":"300462","Order_name":"Paprika rød 15x20 mm 5 kg","Status":"StartedUp","Prod_group":"Annet","Prod_pool":"SF-po-Ind3","Site":"BI-Tranby","Date_delivery":"2026-07-24T12:00:00Z","QTY_scheduled":"40","QTY_good":"40","QTY_remaining":"0","PCT_done":"100"},{"@odata.etag":"","ItemInternalId":"d0a05cef-a440-47bd-8ad3-99ae44a1f66b","Order_nr":"3963071","Item_nr":"300471","Order_name":"Rotgrønnsaker rustikk rå 10 kg","Status":"ReportedFinished","Prod_group":"Industri","Prod_pool":"SF-po-Ind1","Site":"BI-Tranby","Date_delivery":"2026-07-24T12:00:00Z","QTY_scheduled":"450","QTY_good":"450","QTY_remaining":"0","PCT_done":"100"},{"@odata.etag":"","ItemInternalId":"d2068023-bdbb-4af3-b7c4-4eaec19830e7","Order_nr":"3963073","Item_nr":"300454","Order_name":"Kålrot staver industri rå 2,5 kg","Status":"ReportedFinished","Prod_group":"Vakuum","Prod_pool":"SF-po-Vaku","Site":"BI-Tranby","Date_delivery":"2026-07-24T12:00:00Z","QTY_scheduled":"4","QTY_good":"4","QTY_remaining":"0","PCT_done":"100"},{"@odata.etag":"","ItemInternalId":"b7403c91-166d-4c09-a02f-fe466ce8fb69","Order_nr":"3963079","Item_nr":"300096","Order_name":"Babyleaf Mix 65 g NG","Status":"StartedUp","Prod_group":"Dagligvare","Prod_pool":"SF-po-Baby","Site":"BI-Tranby","Date_delivery":"2026-07-24T12:00:00Z","QTY_scheduled":"6500","QTY_good":"6252","QTY_remaining":"248","PCT_done":"96"},{"@odata.etag":"","ItemInternalId":"06683bea-7116-4bfd-8504-8a22ee8b86d9","Order_nr":"3963189","Item_nr":"HF200240","Order_name":"HF Agurk alumette kutt","Status":"ReportedFinished","Prod_group":"HF Kuttetorg","Prod_pool":"SF-K2","Site":"BI-Tranby","Date_delivery":"2026-07-24T12:00:00Z","QTY_scheduled":"49.49","QTY_good":"56.4","QTY_remaining":"0","PCT_done":"114"},{"@odata.etag":"","ItemInternalId":"019489cf-2933-4fe6-a86a-e9ca61c1fb7b","Order_nr":"3963195","Item_nr":"HF200160","Order_name":"HF Råkost mix","Status":"ReportedFinished","Prod_group":"HF Trim","Prod_pool":"SF-T2","Site":"BI-Tranby","Date_delivery":"2026-07-24T12:00:00Z","QTY_scheduled":"438.09","QTY_good":"457.9","QTY_remaining":"0","PCT_done":"105"},{"@odata.etag":"","ItemInternalId":"b8e56982-aa78-4960-935d-3ec088af0e21","Order_nr":"3963237","Item_nr":"HF200137","Order_name":"HF Wok mix 1kg","Status":"ReportedFinished","Prod_group":"HF Trim","Prod_pool":"SF-T1","Site":"BI-Tranby","Date_delivery":"2026-07-24T12:00:00Z","QTY_scheduled":"20.62","QTY_good":"37","QTY_remaining":"0","PCT_done":"179"},{"@odata.etag":"","ItemInternalId":"e3543921-12ff-49aa-887f-5ad735747468","Order_nr":"3963239","Item_nr":"HF200125","Order_name":"HF Salatbar basis","Status":"ReportedFinished","Prod_group":"HF Trim","Prod_pool":"SF-T4","Site":"BI-Tranby","Date_delivery":"2026-07-24T12:00:00Z","QTY_scheduled":"56.7","QTY_good":"61.1","QTY_remaining":"0","PCT_done":"108"},{"@odata.etag":"","ItemInternalId":"c3ac1d68-4e5a-4e9e-b663-e4ca36642782","Order_nr":"3963245","Item_nr":"HF200205","Order_name":"HF Isberg, Kinakål, Crispi, Purre","Status":"ReportedFinished","Prod_group":"HF Trim","Prod_pool":"SF-T3","Site":"BI-Tranby","Date_delivery":"2026-07-24T12:00:00Z","QTY_scheduled":"306.68","QTY_good":"312.8","QTY_remaining":"0","PCT_done":"102"},{"@odata.etag":"","ItemInternalId":"0486484d-8cba-4e66-afb8-8a4eef5fbd56","Order_nr":"3963415","Item_nr":"HF200123","Order_name":"HF Råkost med rødkål og purre","Status":"ReportedFinished","Prod_group":"HF Trim","Prod_pool":"SF-T2","Site":"BI-Tranby","Date_delivery":"2026-07-24T12:00:00Z","QTY_scheduled":"123.71","QTY_good":"127","QTY_remaining":"0","PCT_done":"103"},{"@odata.etag":"","ItemInternalId":"4c152f56-c992-4dac-8623-13e5866310c1","Order_nr":"3963429","Item_nr":"HF200267","Order_name":"HF Grønn paprika skivet 16bl.","Status":"ReportedFinished","Prod_group":"HF Trim","Prod_pool":"SF-T1","Site":"BI-Tranby","Date_delivery":"2026-07-24T12:00:00Z","QTY_scheduled":"41.24","QTY_good":"50","QTY_remaining":"0","PCT_done":"121"},{"@odata.etag":"","ItemInternalId":"a2513858-3f6b-40b9-ae60-59d8e1694471","Order_nr":"3963449","Item_nr":"HF200061","Order_name":"HF Hodekål finstrimlet","Status":"ReportedFinished","Prod_group":"HF Trim","Prod_pool":"SF-T2","Site":"BI-Tranby","Date_delivery":"2026-07-24T12:00:00Z","QTY_scheduled":"164.94","QTY_good":"183","QTY_remaining":"0","PCT_done":"111"},{"@odata.etag":"","ItemInternalId":"36863286-e7ef-4c11-85bd-d32fcb96e358","Order_nr":"3963459","Item_nr":"HF200078","Order_name":"HF Kålrot skrelt 10x10","Status":"StartedUp","Prod_group":"HF Kuttetorg","Prod_pool":"SF-K6","Site":"BI-Tranby","Date_delivery":"2026-07-24T12:00:00Z","QTY_scheduled":"10.31","QTY_good":"11","QTY_remaining":"0","PCT_done":"107"},{"@odata.etag":"","ItemInternalId":"e2c6510e-3129-4e52-9046-febebf57d997","Order_nr":"3963483","Item_nr":"HF200077","Order_name":"HF Kålrot staver","Status":"StartedUp","Prod_group":"HF Kuttetorg","Prod_pool":"SF-K6","Site":"BI-Tranby","Date_delivery":"2026-07-24T12:00:00Z","QTY_scheduled":"10.31","QTY_good":"12.3","QTY_remaining":"0","PCT_done":"119"},{"@odata.etag":"","ItemInternalId":"60eaa3f9-796c-4cf7-b1a8-0e3fea8b4a14","Order_nr":"3963539","Item_nr":"HF200064","Order_name":"HF Hodekål ternet","Status":"ReportedFinished","Prod_group":"HF Trim","Prod_pool":"SF-T2","Site":"BI-Tranby","Date_delivery":"2026-07-24T12:00:00Z","QTY_scheduled":"61.85","QTY_good":"63","QTY_remaining":"0","PCT_done":"102"},{"@odata.etag":"","ItemInternalId":"53a05c17-1f41-4910-8dde-f9d9bb879dff","Order_nr":"3963599","Item_nr":"HF200106","Order_name":"HF Gulrot- pastinakk- båter og kålrot- selleri 10x40 rustikk","Status":"ReportedFinished","Prod_group":"HF Kuttetorg","Prod_pool":"SF-K6","Site":"BI-Tranby","Date_delivery":"2026-07-24T12:00:00Z","QTY_scheduled":"463.9","QTY_good":"509.7","QTY_remaining":"0","PCT_done":"110"},{"@odata.etag":"","ItemInternalId":"253e1f62-9e68-4a56-818c-fe31359c5ddc","Order_nr":"3963601","Item_nr":"HF200239","Order_name":"HF Grønn paprika 10x10 vasket","Status":"ReportedFinished","Prod_group":"HF Kuttetorg","Prod_pool":"SF-K1","Site":"BI-Tranby","Date_delivery":"2026-07-24T12:00:00Z","QTY_scheduled":"41.24","QTY_good":"43.5","QTY_remaining":"0","PCT_done":"105"},{"@odata.etag":"","ItemInternalId":"3550e747-f5a4-49d4-94f8-5edba174d5a2","Order_nr":"3963607","Item_nr":"HF200099","Order_name":"HF Purre ternet","Status":"ReportedFinished","Prod_group":"HF Trim","Prod_pool":"SF-T1","Site":"BI-Tranby","Date_delivery":"2026-07-24T12:00:00Z","QTY_scheduled":"10.31","QTY_good":"11","QTY_remaining":"0","PCT_done":"107"},{"@odata.etag":"","ItemInternalId":"5c76c429-c669-4717-9584-ead3df0d4e5b","Order_nr":"3963611","Item_nr":"HF200045","Order_name":"HF Gul paprika 15x20","Status":"StartedUp","Prod_group":"HF Kuttetorg","Prod_pool":"SF-K1","Site":"BI-Tranby","Date_delivery":"2026-07-24T12:00:00Z","QTY_scheduled":"10.31","QTY_good":"11.3","QTY_remaining":"0","PCT_done":"110"},{"@odata.etag":"","ItemInternalId":"0d7db882-e4a5-4ebf-b83a-4e085763740e","Order_nr":"3963803","Item_nr":"HF200094","Order_name":"HF Pastinakk skrelt","Status":"ReportedFinished","Prod_group":"HF Kuttetorg","Prod_pool":"SF-K3","Site":"BI-Tranby","Date_delivery":"2026-07-24T12:00:00Z","QTY_scheduled":"47.83","QTY_good":"50.9","QTY_remaining":"0","PCT_done":"106"},{"@odata.etag":"","ItemInternalId":"60fa7138-23e4-4c23-b025-291152d0b34f","Order_nr":"3963805","Item_nr":"HF200233","Order_name":"HF Kålrot og Selleri skrelt 10x40x40","Status":"StartedUp","Prod_group":"HF Kuttetorg","Prod_pool":"SF-K6","Site":"BI-Tranby","Date_delivery":"2026-07-24T12:00:00Z","QTY_scheduled":"263.03","QTY_good":"291.8","QTY_remaining":"0","PCT_done":"111"},{"@odata.etag":"","ItemInternalId":"5377d3ca-d26b-4abb-8c85-8f3a5f3155af","Order_nr":"3962457","Item_nr":"300475","Order_name":"Baguettepaprika 250 g 1/6 GN BSH","Status":"ReportedFinished","Prod_group":"Beger","Prod_pool":"SF-be-Gast","Site":"BI-Tranby","Date_delivery":"2026-07-24T12:00:00Z","QTY_scheduled":"16","QTY_good":"12","QTY_remaining":"4","PCT_done":"75"},{"@odata.etag":"","ItemInternalId":"07a19d95-424d-471a-9af3-2b4fdc14f2d8","Order_nr":"3962473","Item_nr":"300382","Order_name":"Kyllingsalat beger 225 g BAMA","Status":"StartedUp","Prod_group":"Beger","Prod_pool":"SF-be-3KB","Site":"BI-Tranby","Date_delivery":"2026-07-24T12:00:00Z","QTY_scheduled":"1600","QTY_good":"1468","QTY_remaining":"132","PCT_done":"92"},{"@odata.etag":"","ItemInternalId":"c538c9b4-328f-4c78-827c-32dc87274f9c","Order_nr":"3962477","Item_nr":"300133","Order_name":"Agurk ternet 800g 1/6 GN SB","Status":"ReportedFinished","Prod_group":"Beger","Prod_pool":"SF-be-Gast","Site":"BI-Tranby","Date_delivery":"2026-07-24T12:00:00Z","QTY_scheduled":"330","QTY_good":"352","QTY_remaining":"0","PCT_done":"107"},{"@odata.etag":"","ItemInternalId":"24d89b2e-1d46-4be5-b03b-2f6a6d06cfb6","Order_nr":"3962489","Item_nr":"300370","Order_name":"Ruccula 65 g Rema","Status":"ReportedFinished","Prod_group":"Dagligvare","Prod_pool":"SF-po-Baby","Site":"BI-Tranby","Date_delivery":"2026-07-24T12:00:00Z","QTY_scheduled":"6200","QTY_good":"6114","QTY_remaining":"86","PCT_done":"99"},{"@odata.etag":"","ItemInternalId":"f0512a8c-f440-4469-ba46-0cb55679e7ef","Order_nr":"3962495","Item_nr":"302021","Order_name":"Pastasalat med Sesamvinaigrette 300 g NG","Status":"StartedUp","Prod_group":"Beger","Prod_pool":"SF-be-180x","Site":"BI-Tranby","Date_delivery":"2026-07-24T12:00:00Z","QTY_scheduled":"900","QTY_good":"936","QTY_remaining":"0","PCT_done":"104"},{"@odata.etag":"","ItemInternalId":"5394b68a-b04d-4c1d-b6a0-b1321c642b44","Order_nr":"3962509","Item_nr":"300371","Order_name":"Babyleaf Mix 65 g Rema","Status":"ReportedFinished","Prod_group":"Dagligvare","Prod_pool":"SF-po-Baby","Site":"BI-Tranby","Date_delivery":"2026-07-24T12:00:00Z","QTY_scheduled":"4100","QTY_good":"4098","QTY_remaining":"2","PCT_done":"100"},{"@odata.etag":"","ItemInternalId":"421bf033-6d17-490c-8229-8d01fc935117","Order_nr":"3962525","Item_nr":"303056","Order_name":"Romano Mix 175 g FP Rema","Status":"ReportedFinished","Prod_group":"Dagligvare","Prod_pool":"SF-p-Va-WA","Site":"BI-Tranby","Date_delivery":"2026-07-24T12:00:00Z","QTY_scheduled":"2400","QTY_good":"2430","QTY_remaining":"0","PCT_done":"101"},{"@odata.etag":"","ItemInternalId":"7feb651c-43fb-4acb-8d4a-8d7e6d0df08e","Order_nr":"3962541","Item_nr":"303579","Order_name":"Egg- & Skinkesalat","Status":"StartedUp","Prod_group":"Beger","Prod_pool":"SF-be-Bm04","Site":"BI-Tranby","Date_delivery":"2026-07-24T12:00:00Z","QTY_scheduled":"300","QTY_good":"292","QTY_remaining":"8","PCT_done":"97"},{"@odata.etag":"","ItemInternalId":"521fdf87-5b35-4a8f-abe7-5eab12ef890c","Order_nr":"3962547","Item_nr":"300392","Order_name":"Løk skivet 1 kg","Status":"ReportedFinished","Prod_group":"Storkjøkken","Prod_pool":"SF-p-Gr-SK","Site":"BI-Tranby","Date_delivery":"2026-07-24T12:00:00Z","QTY_scheduled":"355","QTY_good":"360","QTY_remaining":"0","PCT_done":"101"},{"@odata.etag":"","ItemInternalId":"ae91f855-7f3e-4add-a03b-c242597097e9","Order_nr":"3962557","Item_nr":"300412","Order_name":"Salatblanding Lux 1 kg","Status":"ReportedFinished","Prod_group":"Storkjøkken","Prod_pool":"SF-pm08-10","Site":"BI-Tranby","Date_delivery":"2026-07-24T12:00:00Z","QTY_scheduled":"300","QTY_good":"305","QTY_remaining":"0","PCT_done":"102"},{"@odata.etag":"","ItemInternalId":"18ea8137-1e55-42b7-b6a7-b09b7ac0983a","Order_nr":"3962573","Item_nr":"300411","Order_name":"Råkostsalat 250 g Rema","Status":"ReportedFinished","Prod_group":"Dagligvare","Prod_pool":"SF-p-Me-WA","Site":"BI-Tranby","Date_delivery":"2026-07-24T12:00:00Z","QTY_scheduled":"1300","QTY_good":"1260","QTY_remaining":"40","PCT_done":"97"},{"@odata.etag":"","ItemInternalId":"3b5ebcb1-ead3-4551-973b-ed356efb20f2","Order_nr":"3962577","Item_nr":"300517","Order_name":"Pølseløk 5x5 mm 250 g 1/6 GN","Status":"ReportedFinished","Prod_group":"Beger","Prod_pool":"SF-be-Gast","Site":"BI-Tranby","Date_delivery":"2026-07-24T12:00:00Z","QTY_scheduled":"52","QTY_good":"48","QTY_remaining":"4","PCT_done":"92"},{"@odata.etag":"","ItemInternalId":"df186afb-89f2-4e75-95a4-b3695e755d15","Order_nr":"3962585","Item_nr":"300036","Order_name":"Rød Paprika 700 g Bama","Status":"StartedUp","Prod_group":"Beger","Prod_pool":"SF-be-Gast","Site":"BI-Tranby","Date_delivery":"2026-07-24T12:00:00Z","QTY_scheduled":"360","QTY_good":"356","QTY_remaining":"4","PCT_done":"99"},{"@odata.etag":"","ItemInternalId":"a8cd279a-8c2a-4019-850a-7ab3b4b4fc09","Order_nr":"3962591","Item_nr":"BI620033","Order_name":"Ruccula 65 g NG","Status":"ReportedFinished","Prod_group":"Dagligvare","Prod_pool":"SF-po-Baby","Site":"BI-Tranby","Date_delivery":"2026-07-24T12:00:00Z","QTY_scheduled":"11000","QTY_good":"11766","QTY_remaining":"0","PCT_done":"107"},{"@odata.etag":"","ItemInternalId":"f6833ccf-57fb-44da-b559-70f8ffc3bca7","Order_nr":"3962605","Item_nr":"302017","Order_name":"Brokkolisalat 260g Rema","Status":"ReportedFinished","Prod_group":"Beger","Prod_pool":"SF-be-180x","Site":"BI-Tranby","Date_delivery":"2026-07-24T12:00:00Z","QTY_scheduled":"900","QTY_good":"888","QTY_remaining":"12","PCT_done":"99"},{"@odata.etag":"","ItemInternalId":"834d631b-a3ee-4fb8-89ac-f3e710d9ade8","Order_nr":"3962609","Item_nr":"300437","Order_name":"Bulgursalat 255 g McDonalds","Status":"StartedUp","Prod_group":"Beger","Prod_pool":"SF-be-Bm02","Site":"BI-Tranby","Date_delivery":"2026-07-24T12:00:00Z","QTY_scheduled":"285","QTY_good":"280","QTY_remaining":"5","PCT_done":"98"},{"@odata.etag":"","ItemInternalId":"44880b76-5472-40e7-b186-f7eaa08fc3a0","Order_nr":"3962613","Item_nr":"300110","Order_name":"Ost & Skinkesalat 255 g NG","Status":"ReportedFinished","Prod_group":"Beger","Prod_pool":"SF-be-3KB","Site":"BI-Tranby","Date_delivery":"2026-07-24T12:00:00Z","QTY_scheduled":"300","QTY_good":"364","QTY_remaining":"0","PCT_done":"121"},{"@odata.etag":"","ItemInternalId":"1c69cc79-43b4-49fe-98e9-c5d1e7e225d6","Order_nr":"3962629","Item_nr":"300042","Order_name":"Rødløk ternet 10 mm 1-6 GN SB","Status":"ReportedFinished","Prod_group":"Beger","Prod_pool":"SF-be-Gast","Site":"BI-Tranby","Date_delivery":"2026-07-24T12:00:00Z","QTY_scheduled":"400","QTY_good":"384","QTY_remaining":"16","PCT_done":"96"},{"@odata.etag":"","ItemInternalId":"a40ad068-97df-4e4b-b69d-2c9c7350a1d1","Order_nr":"3962633","Item_nr":"300199","Order_name":"Babyspinat 65 g NG","Status":"StartedUp","Prod_group":"Dagligvare","Prod_pool":"SF-po-Baby","Site":"BI-Tranby","Date_delivery":"2026-07-24T12:00:00Z","QTY_scheduled":"7500","QTY_good":"5652","QTY_remaining":"1848","PCT_done":"75"},{"@odata.etag":"","ItemInternalId":"2f90bbfb-e9d4-40fd-9565-23ec7ae44108","Order_nr":"3962647","Item_nr":"303055","Order_name":"Grønnkål 150 g FP Rema","Status":"StartedUp","Prod_group":"Dagligvare","Prod_pool":"SF-p-Va-WA","Site":"BI-Tranby","Date_delivery":"2026-07-24T12:00:00Z","QTY_scheduled":"1300","QTY_good":"1080","QTY_remaining":"220","PCT_done":"83"},{"@odata.etag":"","ItemInternalId":"e21f243c-1673-4428-97ce-080b1cfad6b5","Order_nr":"3962655","Item_nr":"300473","Order_name":"Middelhavsalat 400 g","Status":"StartedUp","Prod_group":"Storkjøkken","Prod_pool":"SF-pm10","Site":"BI-Tranby","Date_delivery":"2026-07-24T12:00:00Z","QTY_scheduled":"500","QTY_good":"512","QTY_remaining":"0","PCT_done":"102"},{"@odata.etag":"","ItemInternalId":"815b74c8-3fae-4e80-8fe7-dc225d1faa62","Order_nr":"3962665","Item_nr":"300545","Order_name":"Restaurantsalat 400 g","Status":"StartedUp","Prod_group":"Storkjøkken","Prod_pool":"SF-pm08","Site":"BI-Tranby","Date_delivery":"2026-07-24T12:00:00Z","QTY_scheduled":"1500","QTY_good":"640","QTY_remaining":"860","PCT_done":"43"},{"@odata.etag":"","ItemInternalId":"1503a898-a372-42f0-ba2d-625acfa05cf1","Order_nr":"3962669","Item_nr":"300391","Order_name":"Gulrot staver rå 2,5 kg","Status":"ReportedFinished","Prod_group":"Vakuum","Prod_pool":"SF-po-Vaku","Site":"BI-Tranby","Date_delivery":"2026-07-24T12:00:00Z","QTY_scheduled":"52","QTY_good":"52","QTY_remaining":"0","PCT_done":"100"},{"@odata.etag":"","ItemInternalId":"b44611c8-8e56-4ef3-b25c-272c815353fd","Order_nr":"3962689","Item_nr":"300377","Order_name":"Spinat 200 g Rema","Status":"StartedUp","Prod_group":"Dagligvare","Prod_pool":"SF-p-St-WA","Site":"BI-Tranby","Date_delivery":"2026-07-24T12:00:00Z","QTY_scheduled":"2700","QTY_good":"0","QTY_remaining":"2700","PCT_done":"0"},{"@odata.etag":"","ItemInternalId":"1a86b907-ba2e-45b3-8a5c-45c7bf3b0011","Order_nr":"3962697","Item_nr":"300052","Order_name":"Grønnkål Mix 500 g Bama SB","Status":"StartedUp","Prod_group":"Storkjøkken","Prod_pool":"SF-p-Gr-SK","Site":"BI-Tranby","Date_delivery":"2026-07-24T12:00:00Z","QTY_scheduled":"30","QTY_good":"32","QTY_remaining":"0","PCT_done":"107"},{"@odata.etag":"","ItemInternalId":"2818f9f8-10ba-4412-9ea8-6931426afed7","Order_nr":"3962705","Item_nr":"300416","Order_name":"Grønnsaksblanding Julienne 1 kg","Status":"StartedUp","Prod_group":"Storkjøkken","Prod_pool":"SF-p-Gr-SK","Site":"BI-Tranby","Date_delivery":"2026-07-24T12:00:00Z","QTY_scheduled":"70","QTY_good":"0","QTY_remaining":"70","PCT_done":"0"},{"@odata.etag":"","ItemInternalId":"877c189f-d3fe-400e-9e83-6b4437bf6f79","Order_nr":"3962711","Item_nr":"300421","Order_name":"Romano grovkuttet 500 g","Status":"StartedUp","Prod_group":"Storkjøkken","Prod_pool":"SF-pm08","Site":"BI-Tranby","Date_delivery":"2026-07-24T12:00:00Z","QTY_scheduled":"500","QTY_good":"510","QTY_remaining":"0","PCT_done":"102"},{"@odata.etag":"","ItemInternalId":"396bee96-5bc8-45bf-895b-e22bdaf05e80","Order_nr":"3962719","Item_nr":"300109","Order_name":"Isbergsalat 10 mm 700 g SB","Status":"ReportedFinished","Prod_group":"Storkjøkken","Prod_pool":"SF-pm10","Site":"BI-Tranby","Date_delivery":"2026-07-24T12:00:00Z","QTY_scheduled":"550","QTY_good":"591","QTY_remaining":"0","PCT_done":"107"},{"@odata.etag":"","ItemInternalId":"37b61ea5-ed84-4ad3-bd61-c85a3ce8d430","Order_nr":"3962723","Item_nr":"300127","Order_name":"Ruccula Mix 175 g NG","Status":"StartedUp","Prod_group":"Dagligvare","Prod_pool":"SF-p-Va-WA","Site":"BI-Tranby","Date_delivery":"2026-07-24T12:00:00Z","QTY_scheduled":"3500","QTY_good":"3612","QTY_remaining":"0","PCT_done":"103"},{"@odata.etag":"","ItemInternalId":"4a8fb569-0b96-4cec-b278-8d15a41ed4b8","Order_nr":"3962729","Item_nr":"300550","Order_name":"Rødløk ternet 10x10 mm 0,5 kg","Status":"ReportedFinished","Prod_group":"Storkjøkken","Prod_pool":"SF-p-Gr-SK","Site":"BI-Tranby","Date_delivery":"2026-07-24T12:00:00Z","QTY_scheduled":"270","QTY_good":"280","QTY_remaining":"0","PCT_done":"104"},{"@odata.etag":"","ItemInternalId":"da756dee-71a1-4dc9-9f97-31a82afd53e6","Order_nr":"3962733","Item_nr":"300383","Order_name":"Isbergsalat 10 mm 0,5 kg","Status":"ReportedFinished","Prod_group":"Storkjøkken","Prod_pool":"SF-pm10","Site":"BI-Tranby","Date_delivery":"2026-07-24T12:00:00Z","QTY_scheduled":"264","QTY_good":"256","QTY_remaining":"8","PCT_done":"97"},{"@odata.etag":"","ItemInternalId":"cb54ff7d-bd83-4971-917d-5e30b4773b87","Order_nr":"3962737","Item_nr":"300485","Order_name":"Frisée og Ruccula Mix 250 g","Status":"StartedUp","Prod_group":"Storkjøkken","Prod_pool":"SF-pm08","Site":"BI-Tranby","Date_delivery":"2026-07-24T12:00:00Z","QTY_scheduled":"70","QTY_good":"85","QTY_remaining":"0","PCT_done":"121"},{"@odata.etag":"","ItemInternalId":"9bcac11d-c9c0-4014-8710-581684247c8c","Order_nr":"3962743","Item_nr":"300053","Order_name":"Romanosalat 10 mm 500 g SB","Status":"StartedUp","Prod_group":"Storkjøkken","Prod_pool":"SF-pm10","Site":"BI-Tranby","Date_delivery":"2026-07-24T12:00:00Z","QTY_scheduled":"300","QTY_good":"309","QTY_remaining":"0","PCT_done":"103"},{"@odata.etag":"","ItemInternalId":"29ad1190-9d65-4d35-adf9-0cf0e78a5af1","Order_nr":"3962757","Item_nr":"300389","Order_name":"Ruccula vasket 250 g","Status":"StartedUp","Prod_group":"Storkjøkken","Prod_pool":"SF-pm08-10","Site":"BI-Tranby","Date_delivery":"2026-07-24T12:00:00Z","QTY_scheduled":"700","QTY_good":"0","QTY_remaining":"700","PCT_done":"0"},{"@odata.etag":"","ItemInternalId":"62ffe133-90c6-4081-bbc3-92773ccc01b8","Order_nr":"3962761","Item_nr":"301141","Order_name":"Brokkolistilk 5x5 mm 5 kg","Status":"ReportedFinished","Prod_group":"Annet","Prod_pool":"SF-po-Ind3","Site":"BI-Tranby","Date_delivery":"2026-07-24T12:00:00Z","QTY_scheduled":"75","QTY_good":"75","QTY_remaining":"0","PCT_done":"100"},{"@odata.etag":"","ItemInternalId":"d632f727-c7b3-4275-8064-25630a3041a6","Order_nr":"3962773","Item_nr":"303052","Order_name":"Middelhavsalat 80 g FP Rema","Status":"StartedUp","Prod_group":"Dagligvare","Prod_pool":"SF-p-Va-WA","Site":"BI-Tranby","Date_delivery":"2026-07-24T12:00:00Z","QTY_scheduled":"1300","QTY_good":"960","QTY_remaining":"340","PCT_done":"74"},{"@odata.etag":"","ItemInternalId":"e5ceecec-a870-46fb-af53-4194ac6ec9fc","Order_nr":"3962789","Item_nr":"303053","Order_name":"Babyspinat 65 g FP Rema","Status":"ReportedFinished","Prod_group":"Dagligvare","Prod_pool":"SF-po-Baby","Site":"BI-Tranby","Date_delivery":"2026-07-24T12:00:00Z","QTY_scheduled":"3000","QTY_good":"3024","QTY_remaining":"0","PCT_done":"101"},{"@odata.etag":"","ItemInternalId":"3432b987-d502-4c4b-9e46-e62efc413170","Order_nr":"3962803","Item_nr":"300375","Order_name":"Wok Mix 300 g Rema","Status":"StartedUp","Prod_group":"Dagligvare","Prod_pool":"SF-p-Me-WA","Site":"BI-Tranby","Date_delivery":"2026-07-24T12:00:00Z","QTY_scheduled":"1500","QTY_good":"1512","QTY_remaining":"0","PCT_done":"101"},{"@odata.etag":"","ItemInternalId":"8374b182-341e-4f48-b169-1fece66b13fa","Order_nr":"3962807","Item_nr":"300441","Order_name":"Løk skivet 1 kg McDonalds","Status":"ReportedFinished","Prod_group":"Storkjøkken","Prod_pool":"SF-p-Gr-SK","Site":"BI-Tranby","Date_delivery":"2026-07-24T12:00:00Z","QTY_scheduled":"555","QTY_good":"570","QTY_remaining":"0","PCT_done":"103"},{"@odata.etag":"","ItemInternalId":"36c55d88-fa78-4c09-abdd-965913f2ff5a","Order_nr":"3962815","Item_nr":"300380","Order_name":"Bistrosalat 400 g","Status":"StartedUp","Prod_group":"Storkjøkken","Prod_pool":"SF-pm08","Site":"BI-Tranby","Date_delivery":"2026-07-24T12:00:00Z","QTY_scheduled":"800","QTY_good":"815","QTY_remaining":"0","PCT_done":"102"},{"@odata.etag":"","ItemInternalId":"4ba286b2-ef5d-4a17-84eb-d63f24157ff7","Order_nr":"3962829","Item_nr":"302306","Order_name":"Isbergsalat 6x150 g Rema","Status":"ReportedFinished","Prod_group":"Dagligvare","Prod_pool":"SF-p-Me-WA","Site":"BI-Tranby","Date_delivery":"2026-07-24T12:00:00Z","QTY_scheduled":"1400","QTY_good":"1512","QTY_remaining":"0","PCT_done":"108"},{"@odata.etag":"","ItemInternalId":"12eecc10-e1ad-4334-bad0-65562d1c9116","Order_nr":"3962835","Item_nr":"300388","Order_name":"Brokkoli ternet 15x20 mm 1 kg","Status":"StartedUp","Prod_group":"Storkjøkken","Prod_pool":"SF-p-Gr-SK","Site":"BI-Tranby","Date_delivery":"2026-07-24T12:00:00Z","QTY_scheduled":"380","QTY_good":"0","QTY_remaining":"380","PCT_done":"0"},{"@odata.etag":"","ItemInternalId":"d41d0fef-43c9-4b3e-b457-44cde99a39f7","Order_nr":"3962839","Item_nr":"300128","Order_name":"Spinat 200 g NG","Status":"StartedUp","Prod_group":"Dagligvare","Prod_pool":"SF-p-St-WA","Site":"BI-Tranby","Date_delivery":"2026-07-24T12:00:00Z","QTY_scheduled":"2600","QTY_good":"288","QTY_remaining":"2312","PCT_done":"11"},{"@odata.etag":"","ItemInternalId":"ce78eafa-0a79-42f5-80a2-db51b3424130","Order_nr":"3962847","Item_nr":"300424","Order_name":"Spinat vasket 250 g","Status":"StartedUp","Prod_group":"Storkjøkken","Prod_pool":"SF-pm10","Site":"BI-Tranby","Date_delivery":"2026-07-24T12:00:00Z","QTY_scheduled":"120","QTY_good":"0","QTY_remaining":"120","PCT_done":"0"},{"@odata.etag":"","ItemInternalId":"903ab5a1-55ed-4066-8ef4-66d8c9a8925b","Order_nr":"3962861","Item_nr":"302869","Order_name":"Chili Coleslaw 255 g Rema","Status":"ReportedFinished","Prod_group":"Dagligvare","Prod_pool":"SF-p-Me-WA","Site":"BI-Tranby","Date_delivery":"2026-07-24T12:00:00Z","QTY_scheduled":"900","QTY_good":"984","QTY_remaining":"0","PCT_done":"109"},{"@odata.etag":"","ItemInternalId":"a078de56-e33a-43d2-89f5-9c4de6e64637","Order_nr":"3962875","Item_nr":"300399","Order_name":"Grønnkål Mix 500 g","Status":"StartedUp","Prod_group":"Storkjøkken","Prod_pool":"SF-p-Gr-SK","Site":"BI-Tranby","Date_delivery":"2026-07-24T12:00:00Z","QTY_scheduled":"800","QTY_good":"804","QTY_remaining":"0","PCT_done":"100"},{"@odata.etag":"","ItemInternalId":"85aa21a5-2788-450f-ae8f-e518a6e011c4","Order_nr":"3962889","Item_nr":"300366","Order_name":"Meksikansk KIT 270 g Rema","Status":"ReportedFinished","Prod_group":"Dagligvare","Prod_pool":"SF-p-MP-WA","Site":"BI-Tranby","Date_delivery":"2026-07-24T12:00:00Z","QTY_scheduled":"800","QTY_good":"808","QTY_remaining":"0","PCT_done":"101"},{"@odata.etag":"","ItemInternalId":"97dd0750-deda-45c8-923c-ed618a05c798","Order_nr":"3962893","Item_nr":"303531","Order_name":"Kyllingsalat 225 g VM NG","Status":"StartedUp","Prod_group":"Beger","Prod_pool":"SF-be-3KB","Site":"BI-Tranby","Date_delivery":"2026-07-24T12:00:00Z","QTY_scheduled":"1700","QTY_good":"840","QTY_remaining":"860","PCT_done":"49"},{"@odata.etag":"","ItemInternalId":"bd89b0b7-d959-4d53-b885-30306a1ea17b","Order_nr":"3962905","Item_nr":"300381","Order_name":"Isbergsalat 10 mm 1 kg","Status":"ReportedFinished","Prod_group":"Storkjøkken","Prod_pool":"SF-pm08-10","Site":"BI-Tranby","Date_delivery":"2026-07-24T12:00:00Z","QTY_scheduled":"1500","QTY_good":"1495","QTY_remaining":"5","PCT_done":"100"},{"@odata.etag":"","ItemInternalId":"beef6d81-0ca1-491e-8a5c-ab4c68bb7ec2","Order_nr":"3962909","Item_nr":"302877","Order_name":"Kålmix 1 kg","Status":"StartedUp","Prod_group":"Storkjøkken","Prod_pool":"SF-p-Gr-SK","Site":"BI-Tranby","Date_delivery":"2026-07-24T12:00:00Z","QTY_scheduled":"155","QTY_good":"150","QTY_remaining":"5","PCT_done":"97"},{"@odata.etag":"","ItemInternalId":"d80819cc-cd06-4dbe-81a6-d843d36e1b91","Order_nr":"3962915","Item_nr":"300451","Order_name":"Crispi blader vasket 400 g","Status":"StartedUp","Prod_group":"Storkjøkken","Prod_pool":"SF-pm10","Site":"BI-Tranby","Date_delivery":"2026-07-24T12:00:00Z","QTY_scheduled":"300","QTY_good":"0","QTY_remaining":"300","PCT_done":"0"},{"@odata.etag":"","ItemInternalId":"c1a3a681-b531-4369-8b84-158e62c59d9b","Order_nr":"3962931","Item_nr":"300469","Order_name":"Isbergsalat 1 kg Burger King","Status":"ReportedFinished","Prod_group":"Storkjøkken","Prod_pool":"SF-pm08-10","Site":"BI-Tranby","Date_delivery":"2026-07-24T12:00:00Z","QTY_scheduled":"570","QTY_good":"575","QTY_remaining":"0","PCT_done":"101"},{"@odata.etag":"","ItemInternalId":"31a50da2-078d-4618-98c9-9cf3f2d70010","Order_nr":"3962935","Item_nr":"BI620030","Order_name":"Middelhavs Mix 100 g NG","Status":"StartedUp","Prod_group":"Dagligvare","Prod_pool":"SF-p-Va-WA","Site":"BI-Tranby","Date_delivery":"2026-07-24T12:00:00Z","QTY_scheduled":"3400","QTY_good":"0","QTY_remaining":"3400","PCT_done":"0"},{"@odata.etag":"","ItemInternalId":"4564ab1b-a686-49da-8ff9-1d7bd7343478","Order_nr":"3962941","Item_nr":"303533","Order_name":"Ost- og skinkesalat 255 g VM NG","Status":"ReportedFinished","Prod_group":"Beger","Prod_pool":"SF-be-3KB","Site":"BI-Tranby","Date_delivery":"2026-07-24T12:00:00Z","QTY_scheduled":"800","QTY_good":"812","QTY_remaining":"0","PCT_done":"101"},{"@odata.etag":"","ItemInternalId":"ada43c4a-3b0c-4d9f-bd4d-338867ff629d","Order_nr":"3962947","Item_nr":"300478","Order_name":"Isbergsalat Bigmac 1 kg McDonalds","Status":"ReportedFinished","Prod_group":"Storkjøkken","Prod_pool":"SF-pm08-10","Site":"BI-Tranby","Date_delivery":"2026-07-24T12:00:00Z","QTY_scheduled":"3290","QTY_good":"3375","QTY_remaining":"0","PCT_done":"103"},{"@odata.etag":"","ItemInternalId":"3046bec6-8166-40d5-b37f-964e4f312e8b","Order_nr":"3962961","Item_nr":"300410","Order_name":"Ost & Skinke salat beger 255 g BAMA","Status":"ReportedFinished","Prod_group":"Beger","Prod_pool":"SF-be-3KB","Site":"BI-Tranby","Date_delivery":"2026-07-24T12:00:00Z","QTY_scheduled":"1400","QTY_good":"1396","QTY_remaining":"4","PCT_done":"100"},{"@odata.etag":"","ItemInternalId":"68db5ccd-f746-445a-8d4e-b41765855a2e","Order_nr":"3962967","Item_nr":"300143","Order_name":"Gulrot Julienne 400 g SB","Status":"StartedUp","Prod_group":"Storkjøkken","Prod_pool":"SF-p-Gr-SK","Site":"BI-Tranby","Date_delivery":"2026-07-24T12:00:00Z","QTY_scheduled":"240","QTY_good":"244","QTY_remaining":"0","PCT_done":"102"},{"@odata.etag":"","ItemInternalId":"bd2456bf-ff68-43bb-bb43-732aebc0990a","Order_nr":"3962973","Item_nr":"300465","Order_name":"Rødløk ternet 5x5 mm 10 kg","Status":"ReportedFinished","Prod_group":"Annet","Prod_pool":"SF-po-Ind3","Site":"BI-Tranby","Date_delivery":"2026-07-24T12:00:00Z","QTY_scheduled":"600","QTY_good":"50","QTY_remaining":"550","PCT_done":"8"},{"@odata.etag":"","ItemInternalId":"fc8f3123-e606-4cf5-8c32-4ce6696c05cb","Order_nr":"3962977","Item_nr":"300120","Order_name":"Tacosalat beger 242 g NG","Status":"ReportedFinished","Prod_group":"Beger","Prod_pool":"SF-be-3KB","Site":"BI-Tranby","Date_delivery":"2026-07-24T12:00:00Z","QTY_scheduled":"1200","QTY_good":"1212","QTY_remaining":"0","PCT_done":"101"},{"@odata.etag":"","ItemInternalId":"1c3e16f5-7a25-4180-95a1-91c0eb88d743","Order_nr":"3962993","Item_nr":"300376","Order_name":"Tacosalat beger 242 g BAMA","Status":"ReportedFinished","Prod_group":"Beger","Prod_pool":"SF-be-3KB","Site":"BI-Tranby","Date_delivery":"2026-07-24T12:00:00Z","QTY_scheduled":"1300","QTY_good":"1184","QTY_remaining":"116","PCT_done":"91"},{"@odata.etag":"","ItemInternalId":"dcd69429-8e11-4e0c-ac5b-1ba0295d3218","Order_nr":"3962999","Item_nr":"302854","Order_name":"Babyleaf Mix med rødbeter 90 g Rema","Status":"StartedUp","Prod_group":"Dagligvare","Prod_pool":"SF-po-Baby","Site":"BI-Tranby","Date_delivery":"2026-07-24T12:00:00Z","QTY_scheduled":"400","QTY_good":"390","QTY_remaining":"10","PCT_done":"98"},{"@odata.etag":"","ItemInternalId":"33416aca-1b35-4a67-82e5-1c56cb8e43ec","Order_nr":"3963007","Item_nr":"300404","Order_name":"Purre skivet 1 kg","Status":"StartedUp","Prod_group":"Storkjøkken","Prod_pool":"SF-p-Gr-SK","Site":"BI-Tranby","Date_delivery":"2026-07-24T12:00:00Z","QTY_scheduled":"130","QTY_good":"0","QTY_remaining":"130","PCT_done":"0"},{"@odata.etag":"","ItemInternalId":"ebb11927-e2d5-4fa8-a58d-8b8193ce0e4a","Order_nr":"3963011","Item_nr":"303546","Order_name":"Salat Mix 300 g NG","Status":"StartedUp","Prod_group":"Dagligvare","Prod_pool":"SF-p-St-WA","Site":"BI-Tranby","Date_delivery":"2026-07-24T12:00:00Z","QTY_scheduled":"1200","QTY_good":"1225","QTY_remaining":"0","PCT_done":"102"},{"@odata.etag":"","ItemInternalId":"54b3291f-efcd-49f2-b74a-7626aa5b7875","Order_nr":"3963025","Item_nr":"300309","Order_name":"Isberg Mix (6/250 g) Rema","Status":"ReportedFinished","Prod_group":"Dagligvare","Prod_pool":"SF-p-Va-WA","Site":"BI-Tranby","Date_delivery":"2026-07-24T12:00:00Z","QTY_scheduled":"2200","QTY_good":"2286","QTY_remaining":"0","PCT_done":"104"},{"@odata.etag":"","ItemInternalId":"fe9c3149-9c45-466b-9351-42d7ed7b57df","Order_nr":"3963031","Item_nr":"300395","Order_name":"Kinesisk Grøntmix 1 kg","Status":"StartedUp","Prod_group":"Storkjøkken","Prod_pool":"SF-p-Gr-SK","Site":"BI-Tranby","Date_delivery":"2026-07-24T12:00:00Z","QTY_scheduled":"60","QTY_good":"0","QTY_remaining":"60","PCT_done":"0"},{"@odata.etag":"","ItemInternalId":"d237fc19-1685-4f0e-b801-14ca70d6716b","Order_nr":"3963035","Item_nr":"300393","Order_name":"Rødløk skivet 0,5 kg","Status":"ReportedFinished","Prod_group":"Storkjøkken","Prod_pool":"SF-p-Gr-SK","Site":"BI-Tranby","Date_delivery":"2026-07-24T12:00:00Z","QTY_scheduled":"650","QTY_good":"660","QTY_remaining":"0","PCT_done":"102"},{"@odata.etag":"","ItemInternalId":"656c5510-ac48-4f8c-8977-8baf4af40cf5","Order_nr":"3963043","Item_nr":"300308","Order_name":"Grønnkål Mix 250 g 4 po/ks Rema","Status":"StartedUp","Prod_group":"Dagligvare","Prod_pool":"SF-p-Va-WA","Site":"BI-Tranby","Date_delivery":"2026-07-24T12:00:00Z","QTY_scheduled":"500","QTY_good":"0","QTY_remaining":"500","PCT_done":"0"},{"@odata.etag":"","ItemInternalId":"276b7808-b7f4-4477-9605-80d718bd6676","Order_nr":"3963049","Item_nr":"300396","Order_name":"Råkostblanding 1 kg","Status":"ReportedFinished","Prod_group":"Storkjøkken","Prod_pool":"SF-p-Gr-SK","Site":"BI-Tranby","Date_delivery":"2026-07-24T12:00:00Z","QTY_scheduled":"400","QTY_good":"425","QTY_remaining":"0","PCT_done":"106"},{"@odata.etag":"","ItemInternalId":"49cee098-5bf4-4e62-ad47-b31e0007d2a1","Order_nr":"3963053","Item_nr":"300384","Order_name":"Blomkålbuketter 1 kg","Status":"StartedUp","Prod_group":"Storkjøkken","Prod_pool":"SF-p-Gr-SK","Site":"BI-Tranby","Date_delivery":"2026-07-24T12:00:00Z","QTY_scheduled":"85","QTY_good":"0","QTY_remaining":"85","PCT_done":"0"},{"@odata.etag":"","ItemInternalId":"cdee7f2f-bbe9-429e-b75c-fa62d94b0700","Order_nr":"3963059","Item_nr":"300420","Order_name":"Brokkolibuketter 1 kg","Status":"StartedUp","Prod_group":"Storkjøkken","Prod_pool":"SF-p-Gr-SK","Site":"BI-Tranby","Date_delivery":"2026-07-24T12:00:00Z","QTY_scheduled":"30","QTY_good":"0","QTY_remaining":"30","PCT_done":"0"},{"@odata.etag":"","ItemInternalId":"7de5770d-3e07-4ee8-9dc0-804fd9fca481","Order_nr":"3963063","Item_nr":"300481","Order_name":"Tomater BB skivet 1/6 GN","Status":"StartedUp","Prod_group":"Beger","Prod_pool":"SF-be-Gast","Site":"BI-Tranby","Date_delivery":"2026-07-24T12:00:00Z","QTY_scheduled":"2328","QTY_good":"2320","QTY_remaining":"8","PCT_done":"100"},{"@odata.etag":"","ItemInternalId":"e39661ff-64fa-441d-8eb4-0b08fa02f8c8","Order_nr":"3963069","Item_nr":"300400","Order_name":"Gulrot Julienne 1 kg","Status":"StartedUp","Prod_group":"Storkjøkken","Prod_pool":"SF-p-Gr-SK","Site":"BI-Tranby","Date_delivery":"2026-07-24T12:00:00Z","QTY_scheduled":"400","QTY_good":"405","QTY_remaining":"0","PCT_done":"101"},{"@odata.etag":"","ItemInternalId":"6cf9e1f5-a434-4e56-b07b-69b908e5fb8b","Order_nr":"3963077","Item_nr":"303203","Order_name":"Brokkoli og Savoy mix 1 kg","Status":"StartedUp","Prod_group":"Storkjøkken","Prod_pool":"SF-pm08-10","Site":"BI-Tranby","Date_delivery":"2026-07-24T12:00:00Z","QTY_scheduled":"50","QTY_good":"0","QTY_remaining":"50","PCT_done":"0"},{"@odata.etag":"","ItemInternalId":"8fb184ac-7b31-48cd-ba70-10d4c75a65f1","Order_nr":"3963083","Item_nr":"300401","Order_name":"Kinakål kuttet 5 mm 1 kg","Status":"ReportedFinished","Prod_group":"Storkjøkken","Prod_pool":"SF-p-Gr-SK","Site":"BI-Tranby","Date_delivery":"2026-07-24T12:00:00Z","QTY_scheduled":"50","QTY_good":"80","QTY_remaining":"0","PCT_done":"160"},{"@odata.etag":"","ItemInternalId":"40c653dd-2b59-4db2-b254-e8fc18af9e52","Order_nr":"3963087","Item_nr":"300512","Order_name":"Salatløk 5x5 mm 250 g 1/6 GN BSH","Status":"ReportedFinished","Prod_group":"Beger","Prod_pool":"SF-be-Gast","Site":"BI-Tranby","Date_delivery":"2026-07-24T12:00:00Z","QTY_scheduled":"100","QTY_good":"92","QTY_remaining":"8","PCT_done":"92"},{"@odata.etag":"","ItemInternalId":"bc3571ba-b7b8-4859-98ce-a1d8c8581d29","Order_nr":"3963537","Item_nr":"HF200071","Order_name":"HF Kyllingsalat","Status":"ReportedFinished","Prod_group":"HF Trim","Prod_pool":"SF-T3","Site":"BI-Tranby","Date_delivery":"2026-07-24T12:00:00Z","QTY_scheduled":"334.08","QTY_good":"301.5","QTY_remaining":"32.58","PCT_done":"90"},{"@odata.etag":"","ItemInternalId":"eb9f2bd5-feb5-4ff9-a06d-8a85f13e20fb","Order_nr":"3963179","Item_nr":"HF200162","Order_name":"HF Agurk 15x20","Status":"ReportedFinished","Prod_group":"HF Kuttetorg","Prod_pool":"SF-K1","Site":"BI-Tranby","Date_delivery":"2026-07-24T12:00:00Z","QTY_scheduled":"272.15","QTY_good":"280","QTY_remaining":"0","PCT_done":"103"},{"@odata.etag":"","ItemInternalId":"4d2888dd-7196-43ed-ac72-5a3e7584f1eb","Order_nr":"3963551","Item_nr":"HF200108","Order_name":"HF Ruccula","Status":"ReportedFinished","Prod_group":"HF Trim","Prod_pool":"SF-T6","Site":"BI-Tranby","Date_delivery":"2026-07-24T12:00:00Z","QTY_scheduled":"1390.45","QTY_good":"1449.9","QTY_remaining":"0","PCT_done":"104"},{"@odata.etag":"","ItemInternalId":"19e3b438-a9ee-46bf-ad3f-3234e79ccad0","Order_nr":"3963493","Item_nr":"HF200002","Order_name":"HF Babyleaf mix","Status":"ReportedFinished","Prod_group":"HF Trim","Prod_pool":"SF-T6","Site":"BI-Tranby","Date_delivery":"2026-07-24T12:00:00Z","QTY_scheduled":"710.2","QTY_good":"735.6","QTY_remaining":"0","PCT_done":"104"},{"@odata.etag":"","ItemInternalId":"5f475190-24f4-450a-88b2-79d9d4e6c0fc","Order_nr":"3963543","Item_nr":"HF200105","Order_name":"HF Romano mix","Status":"ReportedFinished","Prod_group":"HF Trim","Prod_pool":"SF-T4","Site":"BI-Tranby","Date_delivery":"2026-07-24T12:00:00Z","QTY_scheduled":"1322.12","QTY_good":"1304","QTY_remaining":"18.1199999999997","PCT_done":"99"},{"@odata.etag":"","ItemInternalId":"52a511c4-85e6-40c7-8e73-ef97631c7d4f","Order_nr":"3963613","Item_nr":"HF200110","Order_name":"HF Paprika rød 15x20","Status":"StartedUp","Prod_group":"HF Kuttetorg","Prod_pool":"SF-K1","Site":"BI-Tranby","Date_delivery":"2026-07-24T12:00:00Z","QTY_scheduled":"301.01","QTY_good":"302","QTY_remaining":"0","PCT_done":"100"},{"@odata.etag":"","ItemInternalId":"3757ff56-175c-4807-9a7f-a549997e1e02","Order_nr":"3963559","Item_nr":"HF200122","Order_name":"HF Rødløk ternet 10x10","Status":"ReportedFinished","Prod_group":"HF Kuttetorg","Prod_pool":"SF-K1","Site":"BI-Tranby","Date_delivery":"2026-07-24T12:00:00Z","QTY_scheduled":"386.63","QTY_good":"395","QTY_remaining":"0","PCT_done":"102"},{"@odata.etag":"","ItemInternalId":"62d9b922-a607-41b3-96fb-e1fd98517a2d","Order_nr":"3963565","Item_nr":"HF200132","Order_name":"HF Spinat","Status":"ReportedFinished","Prod_group":"HF Trim","Prod_pool":"SF-T6","Site":"BI-Tranby","Date_delivery":"2026-07-24T12:00:00Z","QTY_scheduled":"1123.78","QTY_good":"1114.2","QTY_remaining":"9.57999999999993","PCT_done":"99"},{"@odata.etag":"","ItemInternalId":"77975e76-a971-4548-b23d-85b0f36a4efa","Order_nr":"3963575","Item_nr":"HF200039","Order_name":"HF Grønnkål mix NG","Status":"ReportedFinished","Prod_group":"HF Trim","Prod_pool":"SF-T2","Site":"BI-Tranby","Date_delivery":"2026-07-24T12:00:00Z","QTY_scheduled":"675.31","QTY_good":"711.3","QTY_remaining":"0","PCT_done":"105"},{"@odata.etag":"","ItemInternalId":"f0c29b5b-df0c-4e2b-8b18-9163687354d5","Order_nr":"3963517","Item_nr":"HF200084","Order_name":"HF Middelhavssalat Rema","Status":"StartedUp","Prod_group":"HF Trim","Prod_pool":"SF-T3","Site":"BI-Tranby","Date_delivery":"2026-07-24T12:00:00Z","QTY_scheduled":"107.25","QTY_good":"106.6","QTY_remaining":"0.650000000000006","PCT_done":"99"},{"@odata.etag":"","ItemInternalId":"996ceb85-1fea-445f-9e77-3ba4a529e679","Order_nr":"3963561","Item_nr":"HF200003","Order_name":"HF Babyspinat","Status":"ReportedFinished","Prod_group":"HF Trim","Prod_pool":"SF-T6","Site":"BI-Tranby","Date_delivery":"2026-07-24T12:00:00Z","QTY_scheduled":"717.68","QTY_good":"621.1","QTY_remaining":"96.5799999999999","PCT_done":"87"},{"@odata.etag":"","ItemInternalId":"74a2d166-8047-4698-9c66-986c3664ba5a","Order_nr":"3963523","Item_nr":"HF200083","Order_name":"HF Meksikansk","Status":"ReportedFinished","Prod_group":"HF Trim","Prod_pool":"SF-T4","Site":"BI-Tranby","Date_delivery":"2026-07-24T12:00:00Z","QTY_scheduled":"464.02","QTY_good":"479.9","QTY_remaining":"0","PCT_done":"103"},{"@odata.etag":"","ItemInternalId":"5c084cd4-f358-4381-9aba-7d3be4a275af","Order_nr":"3963597","Item_nr":"HF200053","Order_name":"HF Gulrot kubb julienne","Status":"ReportedFinished","Prod_group":"HF Kuttetorg","Prod_pool":"SF-K2","Site":"BI-Tranby","Date_delivery":"2026-07-24T12:00:00Z","QTY_scheduled":"511.34","QTY_good":"513","QTY_remaining":"0","PCT_done":"100"},{"@odata.etag":"","ItemInternalId":"e0bcae56-3bfe-4fc6-9e5b-eaf652497bf6","Order_nr":"3963587","Item_nr":"HF200134","Order_name":"HF Tacosalat","Status":"ReportedFinished","Prod_group":"HF Trim","Prod_pool":"SF-T4","Site":"BI-Tranby","Date_delivery":"2026-07-24T12:00:00Z","QTY_scheduled":"353.01","QTY_good":"359.5","QTY_remaining":"0","PCT_done":"102"},{"@odata.etag":"","ItemInternalId":"8f2ca61f-42bb-4fbe-8624-75a5af204517","Order_nr":"3963531","Item_nr":"HF200068","Order_name":"HF Isberg mix","Status":"ReportedFinished","Prod_group":"HF Trim","Prod_pool":"SF-T4","Site":"BI-Tranby","Date_delivery":"2026-07-24T12:00:00Z","QTY_scheduled":"1417.36","QTY_good":"1420.5","QTY_remaining":"0","PCT_done":"100"},{"@odata.etag":"","ItemInternalId":"a31b2ef0-f73e-44e9-91d6-6ff3685747ed","Order_nr":"3963555","Item_nr":"HF200022","Order_name":"HF Bulgur salat","Status":"ReportedFinished","Prod_group":"HF Trim","Prod_pool":"SF-T2","Site":"BI-Tranby","Date_delivery":"2026-07-24T12:00:00Z","QTY_scheduled":"26.99","QTY_good":"29","QTY_remaining":"0","PCT_done":"107"},{"@odata.etag":"","ItemInternalId":"76a491c2-7196-4c0e-a4f5-118b6a454468","Order_nr":"3963571","Item_nr":"HF200081","Order_name":"HF MCD løk skivet","Status":"ReportedFinished","Prod_group":"HF Kuttetorg","Prod_pool":"SF-K1","Site":"BI-Tranby","Date_delivery":"2026-07-24T12:00:00Z","QTY_scheduled":"572.15","QTY_good":"575.8","QTY_remaining":"0","PCT_done":"101"},{"@odata.etag":"","ItemInternalId":"15fa6338-514e-466d-97ba-1be716e345c4","Order_nr":"3963573","Item_nr":"HF200066","Order_name":"HF Isberg 10mm","Status":"ReportedFinished","Prod_group":"HF Trim","Prod_pool":"SF-T3","Site":"BI-Tranby","Date_delivery":"2026-07-24T12:00:00Z","QTY_scheduled":"2295.75","QTY_good":"2301.9","QTY_remaining":"0","PCT_done":"100"},{"@odata.etag":"","ItemInternalId":"d7563bbd-bcfc-4196-a719-ef16ed28f429","Order_nr":"3963583","Item_nr":"HF200005","Order_name":"HF Big Mac isberg","Status":"ReportedFinished","Prod_group":"HF Trim","Prod_pool":"SF-T3","Site":"BI-Tranby","Date_delivery":"2026-07-24T12:00:00Z","QTY_scheduled":"3391.66","QTY_good":"3500.8","QTY_remaining":"0","PCT_done":"103"},{"@odata.etag":"","ItemInternalId":"524590fa-e876-44ae-b7a0-787a52f84fe5","Order_nr":"3963479","Item_nr":"HF200136","Order_name":"HF Tomater BB skivet","Status":"ReportedFinished","Prod_group":"Annet","Prod_pool":"SF-K7","Site":"BI-Tranby","Date_delivery":"2026-07-24T12:00:00Z","QTY_scheduled":"1248.04","QTY_good":"1677.5","QTY_remaining":"0","PCT_done":"134"},{"@odata.etag":"","ItemInternalId":"7eea8c9f-9894-4642-bc08-91be68502b80","Order_nr":"3963407","Item_nr":"HF200126","Order_name":"HF Salatblanding LUX","Status":"ReportedFinished","Prod_group":"HF Trim","Prod_pool":"SF-T4","Site":"BI-Tranby","Date_delivery":"2026-07-24T12:00:00Z","QTY_scheduled":"309.27","QTY_good":"310.7","QTY_remaining":"0","PCT_done":"100"},{"@odata.etag":"","ItemInternalId":"15f698c0-266a-46e4-bc24-ddbf35282c28","Order_nr":"3963579","Item_nr":"HF200028","Order_name":"HF Feldsalat og røde babyleaves","Status":"ReportedFinished","Prod_group":"HF Trim","Prod_pool":"SF-T6","Site":"BI-Tranby","Date_delivery":"2026-07-24T12:00:00Z","QTY_scheduled":"278.19","QTY_good":"332.7","QTY_remaining":"0","PCT_done":"120"},{"@odata.etag":"","ItemInternalId":"6374df8c-ac74-415f-9276-20a979408535","Order_nr":"3963581","Item_nr":"HF200032","Order_name":"HF Frisée","Status":"StartedUp","Prod_group":"HF Trim","Prod_pool":"SF-T3","Site":"BI-Tranby","Date_delivery":"2026-07-24T12:00:00Z","QTY_scheduled":"278.19","QTY_good":"249.8","QTY_remaining":"28.39","PCT_done":"90"},{"@odata.etag":"","ItemInternalId":"e1de4d46-ea57-475e-9253-8c5b71897153","Order_nr":"3963425","Item_nr":"HF200102","Order_name":"HF Restaurant salat","Status":"StartedUp","Prod_group":"HF Trim","Prod_pool":"SF-T4","Site":"BI-Tranby","Date_delivery":"2026-07-24T12:00:00Z","QTY_scheduled":"618.6","QTY_good":"621.6","QTY_remaining":"0","PCT_done":"100"},{"@odata.etag":"","ItemInternalId":"6a0e07df-da57-454d-9290-b0e5eabdc481","Order_nr":"3963427","Item_nr":"HF200057","Order_name":"HF Gulrot kubb staver","Status":"ReportedFinished","Prod_group":"HF Kuttetorg","Prod_pool":"SF-K5","Site":"BI-Tranby","Date_delivery":"2026-07-24T12:00:00Z","QTY_scheduled":"134.02","QTY_good":"140.4","QTY_remaining":"0","PCT_done":"105"},{"@odata.etag":"","ItemInternalId":"7effe4b2-b76e-4634-9cf3-7671aaef780a","Order_nr":"3963603","Item_nr":"HF200041","Order_name":"HF Gulrot- sellerirot- og brokkolistilk julienne","Status":"ReportedFinished","Prod_group":"HF Kuttetorg","Prod_pool":"SF-K2","Site":"BI-Tranby","Date_delivery":"2026-07-24T12:00:00Z","QTY_scheduled":"72.16","QTY_good":"76","QTY_remaining":"0","PCT_done":"105"},{"@odata.etag":"","ItemInternalId":"61eb7e33-88f9-4872-bfad-fb87ad9113bc","Order_nr":"3963227","Item_nr":"HF200035","Order_name":"HF Frisée og ruccula","Status":"StartedUp","Prod_group":"HF Trim","Prod_pool":"SF-T3","Site":"BI-Tranby","Date_delivery":"2026-07-24T12:00:00Z","QTY_scheduled":"18.04","QTY_good":"21.4","QTY_remaining":"0","PCT_done":"119"},{"@odata.etag":"","ItemInternalId":"ff178fc7-3d37-4115-8a71-c23f2e7a7094","Order_nr":"3963439","Item_nr":"HF200016","Order_name":"HF Brokkolistilk 5x5","Status":"ReportedFinished","Prod_group":"HF Kuttetorg","Prod_pool":"SF-K6","Site":"BI-Tranby","Date_delivery":"2026-07-24T12:00:00Z","QTY_scheduled":"77.31","QTY_good":"77.7","QTY_remaining":"0","PCT_done":"101"},{"@odata.etag":"","ItemInternalId":"0cb3b7a3-cbfe-4649-a38d-ee0bcab73162","Order_nr":"3963453","Item_nr":"HF200232","Order_name":"HF Savoykål, Hodekål, Rødkål","Status":"ReportedFinished","Prod_group":"HF Trim","Prod_pool":"SF-T1","Site":"BI-Tranby","Date_delivery":"2026-07-24T12:00:00Z","QTY_scheduled":"159.79","QTY_good":"161","QTY_remaining":"0","PCT_done":"101"},{"@odata.etag":"","ItemInternalId":"fcc6f9f2-5f8f-480c-a2dc-8b4ac3e05266","Order_nr":"3963577","Item_nr":"HF200025","Order_name":"HF Crispi vasket","Status":"ReportedFinished","Prod_group":"HF Trim","Prod_pool":"SF-T3","Site":"BI-Tranby","Date_delivery":"2026-07-24T12:00:00Z","QTY_scheduled":"123.72","QTY_good":"127","QTY_remaining":"0","PCT_done":"103"},{"@odata.etag":"","ItemInternalId":"dcd9a445-4a72-41ae-bc07-8b8abc1059eb","Order_nr":"3963457","Item_nr":"HF200006","Order_name":"HF BK isbergsalat","Status":"ReportedFinished","Prod_group":"HF Trim","Prod_pool":"SF-T3","Site":"BI-Tranby","Date_delivery":"2026-07-24T12:00:00Z","QTY_scheduled":"587.62","QTY_good":"588.9","QTY_remaining":"0","PCT_done":"100"},{"@odata.etag":"","ItemInternalId":"ffa25acf-9fb5-4dba-8e7b-e26e85032429","Order_nr":"3963781","Item_nr":"HF200098","Order_name":"HF Purre skivet 22","Status":"ReportedFinished","Prod_group":"HF Trim","Prod_pool":"SF-T1","Site":"BI-Tranby","Date_delivery":"2026-07-24T12:00:00Z","QTY_scheduled":"176.24","QTY_good":"168","QTY_remaining":"8.24000000000001","PCT_done":"95"},{"@odata.etag":"","ItemInternalId":"d80244a1-a6e2-4478-a940-30f1b154167f","Order_nr":"3963593","Item_nr":"HF200070","Order_name":"HF Kinesisk grøntmix","Status":"ReportedFinished","Prod_group":"HF Trim","Prod_pool":"SF-T2","Site":"BI-Tranby","Date_delivery":"2026-07-24T12:00:00Z","QTY_scheduled":"61.84","QTY_good":"73","QTY_remaining":"0","PCT_done":"118"},{"@odata.etag":"","ItemInternalId":"7913df79-958a-491a-977f-55ffb2b7a2ba","Order_nr":"3963473","Item_nr":"HF200121","Order_name":"HF Rødløk skivet 6mm","Status":"ReportedFinished","Prod_group":"HF Kuttetorg","Prod_pool":"SF-K1","Site":"BI-Tranby","Date_delivery":"2026-07-24T12:00:00Z","QTY_scheduled":"335.07","QTY_good":"338","QTY_remaining":"0","PCT_done":"101"},{"@odata.etag":"","ItemInternalId":"fb886a3f-6d99-464f-8333-4fbd24864bbd","Order_nr":"3963547","Item_nr":"HF200124","Order_name":"HF Råkostsalat","Status":"ReportedFinished","Prod_group":"HF Trim","Prod_pool":"SF-T2","Site":"BI-Tranby","Date_delivery":"2026-07-24T12:00:00Z","QTY_scheduled":"932.96","QTY_good":"970.3","QTY_remaining":"0","PCT_done":"104"},{"@odata.etag":"","ItemInternalId":"5521b3a0-6c74-47b0-938c-54869117340e","Order_nr":"3963343","Item_nr":"HF200011","Order_name":"HF Brokkoli bukett","Status":"ReportedFinished","Prod_group":"HF Kuttetorg","Prod_pool":"SF-K4","Site":"BI-Tranby","Date_delivery":"2026-07-24T12:00:00Z","QTY_scheduled":"30.92","QTY_good":"153.9","QTY_remaining":"0","PCT_done":"498"},{"@odata.etag":"","ItemInternalId":"b3a0061c-55ee-493b-9116-fd7ad367616d","Order_nr":"3963545","Item_nr":"HF200225","Order_name":"HF Savoykål, purre 22bl. og brokkoli 10x10","Status":"ReportedFinished","Prod_group":"HF Trim","Prod_pool":"SF-T1","Site":"BI-Tranby","Date_delivery":"2026-07-24T12:00:00Z","QTY_scheduled":"82.47","QTY_good":"88.5","QTY_remaining":"0","PCT_done":"107"},{"@odata.etag":"","ItemInternalId":"087f2e51-994d-42cc-ac92-4d6b1227e19b","Order_nr":"3963487","Item_nr":"HF200069","Order_name":"HF Kinakål 5mm","Status":"ReportedFinished","Prod_group":"HF Trim","Prod_pool":"SF-T2","Site":"BI-Tranby","Date_delivery":"2026-07-24T12:00:00Z","QTY_scheduled":"51.55","QTY_good":"73","QTY_remaining":"0","PCT_done":"142"},{"@odata.etag":"","ItemInternalId":"a49932ca-70ae-4429-8412-65dab8366a39","Order_nr":"3963541","Item_nr":"HF200206","Order_name":"HF Brokkoli, Rødkål, Purre, Mais 10x10","Status":"ReportedFinished","Prod_group":"HF Kuttetorg","Prod_pool":"SF-K1","Site":"BI-Tranby","Date_delivery":"2026-07-24T12:00:00Z","QTY_scheduled":"92.79","QTY_good":"94","QTY_remaining":"0","PCT_done":"101"},{"@odata.etag":"","ItemInternalId":"c9db4704-a6d0-47f9-9b61-a9a0848c721d","Order_nr":"3963405","Item_nr":"HF200079","Order_name":"HF Gul løk skivet 6mm","Status":"ReportedFinished","Prod_group":"HF Kuttetorg","Prod_pool":"SF-K1","Site":"BI-Tranby","Date_delivery":"2026-07-24T12:00:00Z","QTY_scheduled":"365.97","QTY_good":"369","QTY_remaining":"0","PCT_done":"101"},{"@odata.etag":"","ItemInternalId":"50478116-17b2-4b23-bc2c-7ece284bb7c0","Order_nr":"3963553","Item_nr":"HF200020","Order_name":"HF Brokkolisalat kit 10x10","Status":"ReportedFinished","Prod_group":"HF Kuttetorg","Prod_pool":"SF-K1","Site":"BI-Tranby","Date_delivery":"2026-07-24T12:00:00Z","QTY_scheduled":"332.4","QTY_good":"338","QTY_remaining":"0","PCT_done":"102"},{"@odata.etag":"","ItemInternalId":"00a08c9e-9ed7-485a-8bd4-aed7b4e3aa14","Order_nr":"3963557","Item_nr":"HF200087","Order_name":"HF Ost- og skinke salat","Status":"ReportedFinished","Prod_group":"HF Trim","Prod_pool":"SF-T4","Site":"BI-Tranby","Date_delivery":"2026-07-24T12:00:00Z","QTY_scheduled":"360.75","QTY_good":"372.7","QTY_remaining":"0","PCT_done":"103"},{"@odata.etag":"","ItemInternalId":"ed45a189-032e-48de-be79-f90744c344e1","Order_nr":"3963563","Item_nr":"HF200038","Order_name":"HF Grønnkål strimlet 16bl","Status":"ReportedFinished","Prod_group":"HF Trim","Prod_pool":"SF-T2","Site":"BI-Tranby","Date_delivery":"2026-07-24T12:00:00Z","QTY_scheduled":"355.58","QTY_good":"360.9","QTY_remaining":"0","PCT_done":"101"},{"@odata.etag":"","ItemInternalId":"e0fe10ca-a81a-4b63-ba7e-5b4cc16c26f8","Order_nr":"3963567","Item_nr":"HF200109","Order_name":"HF Ruccula mix","Status":"ReportedFinished","Prod_group":"HF Trim","Prod_pool":"SF-T4","Site":"BI-Tranby","Date_delivery":"2026-07-24T12:00:00Z","QTY_scheduled":"631.4","QTY_good":"637.2","QTY_remaining":"0","PCT_done":"101"},{"@odata.etag":"","ItemInternalId":"b4dc6ee2-d2c8-4558-b094-85af8df2ceb5","Order_nr":"3963515","Item_nr":"HF200103","Order_name":"HF Romano 10mm","Status":"ReportedFinished","Prod_group":"HF Trim","Prod_pool":"SF-T3","Site":"BI-Tranby","Date_delivery":"2026-07-24T12:00:00Z","QTY_scheduled":"154.66","QTY_good":"159.5","QTY_remaining":"0","PCT_done":"103"},{"@odata.etag":"","ItemInternalId":"959fb433-d60e-4906-88c7-0ca6f0de804d","Order_nr":"3963569","Item_nr":"HF200174","Order_name":"HF Wok mix","Status":"ReportedFinished","Prod_group":"HF Trim","Prod_pool":"SF-T2","Site":"BI-Tranby","Date_delivery":"2026-07-24T12:00:00Z","QTY_scheduled":"804.18","QTY_good":"807.2","QTY_remaining":"0","PCT_done":"100"},{"@odata.etag":"","ItemInternalId":"38e5c0ce-3bb9-41a0-80ae-82e43816bf1b","Order_nr":"3963609","Item_nr":"HF200014","Order_name":"HF Brokkoli ternet 15x20","Status":"ReportedFinished","Prod_group":"HF Kuttetorg","Prod_pool":"SF-K1","Site":"BI-Tranby","Date_delivery":"2026-07-24T12:00:00Z","QTY_scheduled":"391.74","QTY_good":"391.7","QTY_remaining":"0.0400000000000205","PCT_done":"100"},{"@odata.etag":"","ItemInternalId":"5193f0e1-a2d2-4e66-88d3-0494efc3c68d","Order_nr":"3963465","Item_nr":"HF200230","Order_name":"HF Rødbeter, Rød rhubarb, Feld salat, Ruccula, Bulls blood","Status":"ReportedFinished","Prod_group":"HF Trim","Prod_pool":"SF-T6","Site":"BI-Tranby","Date_delivery":"2026-07-24T12:00:00Z","QTY_scheduled":"37.13","QTY_good":"34.6","QTY_remaining":"2.53","PCT_done":"93"},{"@odata.etag":"","ItemInternalId":"2700302f-a1a0-4d15-a9f4-274be0cd7364","Order_nr":"3963591","Item_nr":"HF200218","Order_name":"HF Salatmiks","Status":"StartedUp","Prod_group":"HF Trim","Prod_pool":"SF-T4","Site":"BI-Tranby","Date_delivery":"2026-07-24T12:00:00Z","QTY_scheduled":"371.16","QTY_good":"381.6","QTY_remaining":"0","PCT_done":"103"},{"@odata.etag":"","ItemInternalId":"d49088a7-5423-4f0d-8fdc-fd0c4a48d24f","Order_nr":"3963533","Item_nr":"HF200040","Order_name":"HF Grønnkål mix Rema","Status":"ReportedFinished","Prod_group":"HF Trim","Prod_pool":"SF-T2","Site":"BI-Tranby","Date_delivery":"2026-07-24T12:00:00Z","QTY_scheduled":"128.86","QTY_good":"157.4","QTY_remaining":"0","PCT_done":"122"},{"@odata.etag":"","ItemInternalId":"3a27cff4-587d-4d8d-9a65-17d2d93389ee","Order_nr":"3963435","Item_nr":"HF200104","Order_name":"HF Romano grovkuttet","Status":"ReportedFinished","Prod_group":"HF Trim","Prod_pool":"SF-T3","Site":"BI-Tranby","Date_delivery":"2026-07-24T12:00:00Z","QTY_scheduled":"257.75","QTY_good":"265.7","QTY_remaining":"0","PCT_done":"103"},{"@odata.etag":"","ItemInternalId":"8e73ea4e-a831-4797-b20a-3a9cd7e5a22a","Order_nr":"3963535","Item_nr":"HF200004","Order_name":"HF Baguette paprika","Status":"ReportedFinished","Prod_group":"HF Trim","Prod_pool":"SF-T2","Site":"BI-Tranby","Date_delivery":"2026-07-24T12:00:00Z","QTY_scheduled":"4.12","QTY_good":"5.9","QTY_remaining":"0","PCT_done":"143"},{"@odata.etag":"","ItemInternalId":"00a6b4f3-bcec-4116-b31e-9ffdc18eb218","Order_nr":"3963605","Item_nr":"HF200044","Order_name":"HF Gul løk 5x5","Status":"ReportedFinished","Prod_group":"HF Kuttetorg","Prod_pool":"SF-K6","Site":"BI-Tranby","Date_delivery":"2026-07-24T12:00:00Z","QTY_scheduled":"23.71","QTY_good":"24.1","QTY_remaining":"0","PCT_done":"102"},{"@odata.etag":"","ItemInternalId":"15c3b505-1924-40c8-90a4-c94c3d2d9453","Order_nr":"3963595","Item_nr":"HF200008","Order_name":"HF Blomkålbuketter","Status":"ReportedFinished","Prod_group":"HF Kuttetorg","Prod_pool":"SF-K4","Site":"BI-Tranby","Date_delivery":"2026-07-24T12:00:00Z","QTY_scheduled":"87.62","QTY_good":"92.7","QTY_remaining":"0","PCT_done":"106"},{"@odata.etag":"","ItemInternalId":"2e29e5e5-3dc9-4f18-9773-8310a30b8b7f","Order_nr":"3963615","Item_nr":"HF200120","Order_name":"HF Rødløk 5x5","Status":"ReportedFinished","Prod_group":"HF Kuttetorg","Prod_pool":"SF-K6","Site":"BI-Tranby","Date_delivery":"2026-07-24T12:00:00Z","QTY_scheduled":"644.31","QTY_good":"78.5","QTY_remaining":"565.81","PCT_done":"12"},{"@odata.etag":"","ItemInternalId":"d6d1ca61-0a5f-4499-9ba5-606e5ff9ce42","Order_nr":"3963783","Item_nr":"HF200115","Order_name":"HF Rødkål strimlet","Status":"ReportedFinished","Prod_group":"HF Trim","Prod_pool":"SF-T1","Site":"BI-Tranby","Date_delivery":"2026-07-24T12:00:00Z","QTY_scheduled":"349.97","QTY_good":"155","QTY_remaining":"194.97","PCT_done":"44"},{"@odata.etag":"","ItemInternalId":"7f662770-27dc-4ed1-a891-ede1cc0a5d8b","Order_nr":"3963785","Item_nr":"HF200101","Order_name":"HF Radicchio","Status":"StartedUp","Prod_group":"HF Trim","Prod_pool":"SF-T4","Site":"BI-Tranby","Date_delivery":"2026-07-24T12:00:00Z","QTY_scheduled":"499.64","QTY_good":"669.7","QTY_remaining":"0","PCT_done":"134"},{"@odata.etag":"","ItemInternalId":"b4220f4f-b31b-4086-99b5-96961cbff22b","Order_nr":"3963797","Item_nr":"HF200055","Order_name":"HF Gulrot- og rødbet julienne","Status":"ReportedFinished","Prod_group":"HF Kuttetorg","Prod_pool":"SF-K2","Site":"BI-Tranby","Date_delivery":"2026-07-24T12:00:00Z","QTY_scheduled":"207.24","QTY_good":"219.5","QTY_remaining":"0","PCT_done":"106"},{"@odata.etag":"","ItemInternalId":"c3826f4f-cab1-423c-bab8-6721f2b389dd","Order_nr":"3963777","Item_nr":"HF200072","Order_name":"HF Hodekål, purre og gulrotblanding","Status":"ReportedFinished","Prod_group":"HF Trim","Prod_pool":"SF-T1","Site":"BI-Tranby","Date_delivery":"2026-07-24T12:00:00Z","QTY_scheduled":"244.49","QTY_good":"271","QTY_remaining":"0","PCT_done":"111"},{"@odata.etag":"","ItemInternalId":"619c267f-88d6-4131-9627-7122ca48c390","Order_nr":"3963799","Item_nr":"HF200073","Order_name":"HF Hodekål, rødkål, gulrot, mais","Status":"ReportedFinished","Prod_group":"HF Trim","Prod_pool":"SF-T1","Site":"BI-Tranby","Date_delivery":"2026-07-24T12:00:00Z","QTY_scheduled":"236.56","QTY_good":"267","QTY_remaining":"0","PCT_done":"113"},{"@odata.etag":"","ItemInternalId":"533df470-3471-42fb-b83e-dfc2a807a10f","Order_nr":"3963879","Item_nr":"HF200050","Order_name":"HF Gulrot julienne","Status":"ReportedFinished","Prod_group":"HF Kuttetorg","Prod_pool":"SF-K2","Site":"BI-Tranby","Date_delivery":"2026-07-24T12:00:00Z","QTY_scheduled":"1011.44","QTY_good":"1049.7","QTY_remaining":"0","PCT_done":"104"},{"@odata.etag":"","ItemInternalId":"a8793d7e-4b61-470b-9091-977a6aba85e8","Order_nr":"3963791","Item_nr":"HF200018","Order_name":"HF Brokkolistilk- og gulrot julienne 50/50","Status":"ReportedFinished","Prod_group":"HF Kuttetorg","Prod_pool":"SF-K2","Site":"BI-Tranby","Date_delivery":"2026-07-24T12:00:00Z","QTY_scheduled":"15.46","QTY_good":"17","QTY_remaining":"0","PCT_done":"110"},{"@odata.etag":"","ItemInternalId":"bafbccf0-523f-404a-9ad5-df1518b51cc6","Order_nr":"3963741","Item_nr":"HF200034","Order_name":"HF Frisée og radicchio 50/50","Status":"StartedUp","Prod_group":"HF Trim","Prod_pool":"SF-T4","Site":"BI-Tranby","Date_delivery":"2026-07-24T12:00:00Z","QTY_scheduled":"75.47","QTY_good":"94","QTY_remaining":"0","PCT_done":"125"},{"@odata.etag":"","ItemInternalId":"7a4c89ea-ddf9-4984-9b35-1fb3e10a3acf","Order_nr":"3963881","Item_nr":"HF200128","Order_name":"HF Sellerirot skrelt","Status":"ReportedFinished","Prod_group":"HF Kuttetorg","Prod_pool":"SF-K3","Site":"BI-Tranby","Date_delivery":"2026-07-24T12:00:00Z","QTY_scheduled":"117.83","QTY_good":"137.2","QTY_remaining":"0","PCT_done":"116"},{"@odata.etag":"","ItemInternalId":"70ccd4f1-ba24-444d-92b2-a94691027776","Order_nr":"3963801","Item_nr":"HF200054","Order_name":"HF Gulrot- og kålrot julienne","Status":"ReportedFinished","Prod_group":"HF Kuttetorg","Prod_pool":"SF-K2","Site":"BI-Tranby","Date_delivery":"2026-07-24T12:00:00Z","QTY_scheduled":"17.53","QTY_good":"19.9","QTY_remaining":"0","PCT_done":"114"},{"@odata.etag":"","ItemInternalId":"25a06c93-718e-4f51-8b8e-63781ed32f95","Order_nr":"3963787","Item_nr":"HF200212","Order_name":"HF Brokkoli ternet 10x10","Status":"ReportedFinished","Prod_group":"HF Kuttetorg","Prod_pool":"SF-K1","Site":"BI-Tranby","Date_delivery":"2026-07-24T12:00:00Z","QTY_scheduled":"36.55","QTY_good":"37.4","QTY_remaining":"0","PCT_done":"102"},{"@odata.etag":"","ItemInternalId":"aa1a6a6b-342b-4771-b1d6-318ccd77c0c5","Order_nr":"3963793","Item_nr":"HF200033","Order_name":"HF Frisée og Radiccchio 60/40","Status":"StartedUp","Prod_group":"HF Trim","Prod_pool":"SF-T4","Site":"BI-Tranby","Date_delivery":"2026-07-24T12:00:00Z","QTY_scheduled":"162.71","QTY_good":"165","QTY_remaining":"0","PCT_done":"101"},{"@odata.etag":"","ItemInternalId":"ce042a86-721b-4caa-aee7-68de587a0006","Order_nr":"3963795","Item_nr":"HF200012","Order_name":"HF Brokkoli buketter små","Status":"ReportedFinished","Prod_group":"HF Kuttetorg","Prod_pool":"SF-K4","Site":"BI-Tranby","Date_delivery":"2026-07-24T12:00:00Z","QTY_scheduled":"190.67","QTY_good":"189.3","QTY_remaining":"1.36999999999998","PCT_done":"99"},{"@odata.etag":"","ItemInternalId":"1869d8e7-2070-45ad-bb7d-7e0e2f7bdb87","Order_nr":"3963755","Item_nr":"HF200221","Order_name":"HF Rødbet alumett kutt","Status":"ReportedFinished","Prod_group":"HF Kuttetorg","Prod_pool":"SF-K2","Site":"BI-Tranby","Date_delivery":"2026-07-24T12:00:00Z","QTY_scheduled":"16.84","QTY_good":"20.8","QTY_remaining":"0","PCT_done":"124"},{"@odata.etag":"","ItemInternalId":"1bb907b2-3e84-417c-9e49-d1397981684a","Order_nr":"3963877","Item_nr":"HF200113","Order_name":"HF Rødbete skrelt","Status":"ReportedFinished","Prod_group":"HF Kuttetorg","Prod_pool":"SF-K3","Site":"BI-Tranby","Date_delivery":"2026-07-24T12:00:00Z","QTY_scheduled":"145.57","QTY_good":"152.5","QTY_remaining":"0","PCT_done":"105"},{"@odata.etag":"","ItemInternalId":"269ce8d6-6049-45ab-b16a-fb000e048fe5","Order_nr":"3963891","Item_nr":"300543","Order_name":"Råkostblanding m/rødkål og purre 1 kg","Status":"StartedUp","Prod_group":"Storkjøkken","Prod_pool":"SF-p-Gr-SK","Site":"BI-Tranby","Date_delivery":"2026-07-24T12:00:00Z","QTY_scheduled":"80","QTY_good":"0","QTY_remaining":"80","PCT_done":"0"}]